[
  {
    "Id": 1,
    "name": "Wireless Headphones",
    "sku": "WH-001",
    "quantity": 45,
    "price": 129.99,
    "category": "Electronics",
    "minStock": 10,
    "description": "High-quality wireless Bluetooth headphones with noise cancellation",
    "createdAt": "2024-01-15T10:30:00Z",
    "updatedAt": "2024-01-20T14:45:00Z"
  },
  {
    "Id": 2,
    "name": "Coffee Maker",
    "sku": "CM-002",
    "quantity": 8,
    "price": 89.99,
    "category": "Kitchen",
    "minStock": 15,
    "description": "Programmable 12-cup coffee maker with thermal carafe",
    "createdAt": "2024-01-16T09:15:00Z",
    "updatedAt": "2024-01-21T11:20:00Z"
  },
  {
    "Id": 3,
    "name": "Office Chair",
    "sku": "OC-003",
    "quantity": 22,
    "price": 199.99,
    "category": "Furniture",
    "minStock": 5,
    "description": "Ergonomic office chair with lumbar support and adjustable height",
    "createdAt": "2024-01-17T13:45:00Z",
    "updatedAt": "2024-01-22T16:30:00Z"
  },
  {
    "Id": 4,
    "name": "Smartphone Case",
    "sku": "SC-004",
    "quantity": 3,
    "price": 24.99,
    "category": "Electronics",
    "minStock": 20,
    "description": "Protective smartphone case with shock absorption",
    "createdAt": "2024-01-18T08:20:00Z",
    "updatedAt": "2024-01-23T10:15:00Z"
  },
  {
    "Id": 5,
    "name": "Desk Lamp",
    "sku": "DL-005",
    "quantity": 15,
    "price": 49.99,
    "category": "Furniture",
    "minStock": 8,
    "description": "LED desk lamp with adjustable brightness and USB charging port",
    "createdAt": "2024-01-19T11:30:00Z",
    "updatedAt": "2024-01-24T09:45:00Z"
  },
  {
    "Id": 6,
    "name": "Blender",
    "sku": "BL-006",
    "quantity": 12,
    "price": 79.99,
    "category": "Kitchen",
    "minStock": 10,
    "description": "High-speed blender with multiple speed settings and pulse function",
    "createdAt": "2024-01-20T14:15:00Z",
    "updatedAt": "2024-01-25T12:30:00Z"
  },
  {
    "Id": 7,
    "name": "Tablet Stand",
    "sku": "TS-007",
    "quantity": 5,
    "price": 19.99,
    "category": "Electronics",
    "minStock": 12,
    "description": "Adjustable tablet stand compatible with most tablet sizes",
    "createdAt": "2024-01-21T16:45:00Z",
    "updatedAt": "2024-01-26T08:20:00Z"
  },
  {
    "Id": 8,
    "name": "Bookshelf",
    "sku": "BS-008",
    "quantity": 7,
    "price": 149.99,
    "category": "Furniture",
    "minStock": 3,
    "description": "5-tier wooden bookshelf with modern design",
    "createdAt": "2024-01-22T10:00:00Z",
    "updatedAt": "2024-01-27T13:15:00Z"
  },
  {
    "Id": 9,
    "name": "Kitchen Scale",
    "sku": "KS-009",
    "quantity": 18,
    "price": 34.99,
    "category": "Kitchen",
    "minStock": 8,
    "description": "Digital kitchen scale with precision measurement up to 11 lbs",
    "createdAt": "2024-01-23T12:30:00Z",
    "updatedAt": "2024-01-28T15:45:00Z"
  },
  {
    "Id": 10,
    "name": "Wireless Mouse",
    "sku": "WM-010",
    "quantity": 2,
    "price": 39.99,
    "category": "Electronics",
    "minStock": 15,
    "description": "Ergonomic wireless mouse with long battery life",
    "createdAt": "2024-01-24T09:45:00Z",
    "updatedAt": "2024-01-29T11:30:00Z"
  },
  {
    "Id": 11,
    "name": "Standing Desk",
    "sku": "SD-011",
    "quantity": 4,
    "price": 299.99,
    "category": "Furniture",
    "minStock": 2,
    "description": "Height-adjustable standing desk with electric motor",
    "createdAt": "2024-01-25T15:20:00Z",
    "updatedAt": "2024-01-30T14:10:00Z"
  },
  {
    "Id": 12,
    "name": "Air Fryer",
    "sku": "AF-012",
    "quantity": 9,
    "price": 119.99,
    "category": "Kitchen",
    "minStock": 6,
    "description": "Compact air fryer with digital controls and dishwasher-safe basket",
    "createdAt": "2024-01-26T11:15:00Z",
    "updatedAt": "2024-01-31T16:25:00Z"
  }
]